Metadata-Version: 2.1
Name: slashpy
Version: 0.1.1
Summary: Discord Slash command builder made in Python
Home-page: https://github.com/AlexFlipnote/discord_slash.py
Author: AlexFlipnote
License: MIT
Project-URL: Code, https://github.com/AlexFlipnote/discord_slash.py/
Project-URL: Issue tracker, https://github.com/AlexFlipnote/discord_slash.py/issues
Platform: UNKNOWN
Classifier: License :: OSI Approved :: MIT License
Requires-Python: >=3.6
